libertem_jupyter_proxy/__init__.py
libertem_jupyter_proxy/icons/libertem.svg
libertem_jupyter_proxy/share/launch_juwels.sh
libertem_jupyter_proxy-0.1.2.dist-info/LICENSE
libertem_jupyter_proxy-0.1.2.dist-info/METADATA
libertem_jupyter_proxy-0.1.2.dist-info/WHEEL
libertem_jupyter_proxy-0.1.2.dist-info/entry_points.txt
libertem_jupyter_proxy-0.1.2.dist-info/top_level.txt
libertem_jupyter_proxy-0.1.2.dist-info/RECORD
