Metadata-Version: 2.1
Name: libertem-jupyter-proxy
Version: 0.1.2
Summary: Run LiberTEM via JupyterLab/JupyterHub
Home-page: https://github.com/LiberTEM/LiberTEM-jupyter-proxy
Author: 
License: BSD
Keywords: Jupyter
Platform: UNKNOWN
Classifier: Framework :: Jupyter
Requires-Dist: jupyter-server-proxy
